{
  "response": "OK",
  "metadata_uri": "ipfs://bafkreiaw37qarysifrvja77nzopz3klczxqzzftt2gc3d3hhtuhgl2h7x4",
  "name": "Fantasy Planet #1276",
  "description": "Which Fantasy Planet will you get?",
  "file_url": "https://ipfs.io/ipfs/bafybeihyajgw5iqn5x3ghnv64ogh7izctjjh3lksqjvh56bn32lbcehiaq",
  "external_url": "https://www.fantasyplanets.world",
  "animation_url": null,
  "custom_fields": {
    "edition": 1,
    "date": 1653823192508,
    "compiler": "Fantasy Art Generator v1.3"
  },
  "attributes": null
}