{
  "response": "OK",
  "metadata_uri": "ipfs://bafkreibn2ce5azwhvddiowaes6yzrwdnao7npifcr77fyvm7eijeoeks2i",
  "name": "Fantasy Planet #135",
  "description": "Which Fantasy Planet will you get?",
  "file_url": "https://ipfs.io/ipfs/bafybeihyajgw5iqn5x3ghnv64ogh7izctjjh3lksqjvh56bn32lbcehiaq",
  "external_url": "https://www.fantasyplanets.world",
  "animation_url": null,
  "custom_fields": {
    "edition": 1,
    "date": 1653743762798,
    "compiler": "Fantasy Art Generator v1.3"
  },
  "attributes": null
}