{
  "response": "OK",
  "metadata_uri": "ipfs://bafkreid5wabvhk4clq3tu6m6rtuouxvguahfgqnurd76gevkrhh5r3fyqe",
  "name": "Fantasy Planet #1551",
  "description": "Which Fantasy Planet will you get?",
  "file_url": "https://ipfs.io/ipfs/bafybeihyajgw5iqn5x3ghnv64ogh7izctjjh3lksqjvh56bn32lbcehiaq",
  "external_url": "https://www.fantasyplanets.world",
  "animation_url": null,
  "custom_fields": {
    "edition": 1,
    "date": 1653842035029,
    "compiler": "Fantasy Art Generator v1.3"
  },
  "attributes": null
}