{
  "response": "OK",
  "metadata_uri": "ipfs://bafkreidjfgf24gy5iytdpum6mlycrwythcrqp47ogz6gtp2hg2z245mufq",
  "name": "Fantasy Planet #1999",
  "description": "Which Fantasy Planet will you get?",
  "file_url": "https://ipfs.io/ipfs/bafybeihyajgw5iqn5x3ghnv64ogh7izctjjh3lksqjvh56bn32lbcehiaq",
  "external_url": "https://www.fantasyplanets.world",
  "animation_url": null,
  "custom_fields": {
    "edition": 1,
    "date": 1653873134584,
    "compiler": "Fantasy Art Generator v1.3"
  },
  "attributes": null
}