{
  "response": "OK",
  "metadata_uri": "ipfs://bafkreihgjl6tucwqpie7vf7s2hg3p3ylcqxfwn5htspj7v4jpr6hsbuasa",
  "name": "Fantasy Planet #2294",
  "description": "Which Fantasy Planet will you get?",
  "file_url": "https://ipfs.io/ipfs/bafybeihyajgw5iqn5x3ghnv64ogh7izctjjh3lksqjvh56bn32lbcehiaq",
  "external_url": "https://www.fantasyplanets.world",
  "animation_url": null,
  "custom_fields": {
    "edition": 1,
    "date": 1653893917315,
    "compiler": "Fantasy Art Generator v1.3"
  },
  "attributes": null
}