{
  "response": "OK",
  "metadata_uri": "ipfs://bafkreif4sxhuwokjnnzavtjie6x3qegexnk4aja2mptmdbc4ct2vtzihim",
  "name": "Fantasy Planet #2459",
  "description": "Which Fantasy Planet will you get?",
  "file_url": "https://ipfs.io/ipfs/bafybeihyajgw5iqn5x3ghnv64ogh7izctjjh3lksqjvh56bn32lbcehiaq",
  "external_url": "https://www.fantasyplanets.world",
  "animation_url": null,
  "custom_fields": {
    "edition": 1,
    "date": 1653905579784,
    "compiler": "Fantasy Art Generator v1.3"
  },
  "attributes": null
}