{
  "response": "OK",
  "metadata_uri": "ipfs://bafkreib4nw4yhsojqfjhw63vdsyj3z47xqlx3gyllgpfvi7initgysm4oq",
  "name": "Fantasy Planet #2627",
  "description": "Which Fantasy Planet will you get?",
  "file_url": "https://ipfs.io/ipfs/bafybeihyajgw5iqn5x3ghnv64ogh7izctjjh3lksqjvh56bn32lbcehiaq",
  "external_url": "https://www.fantasyplanets.world",
  "animation_url": null,
  "custom_fields": {
    "edition": 1,
    "date": 1653917358748,
    "compiler": "Fantasy Art Generator v1.3"
  },
  "attributes": null
}