{
  "response": "OK",
  "metadata_uri": "ipfs://bafkreigchjl3qc4xyiptvk7urmtjvj2ykzwsz3q6mfbh2rz7hdbnckdkma",
  "name": "Fantasy Planet #2885",
  "description": "Which Fantasy Planet will you get?",
  "file_url": "https://ipfs.io/ipfs/bafybeihyajgw5iqn5x3ghnv64ogh7izctjjh3lksqjvh56bn32lbcehiaq",
  "external_url": "https://www.fantasyplanets.world",
  "animation_url": null,
  "custom_fields": {
    "edition": 1,
    "date": 1653935176373,
    "compiler": "Fantasy Art Generator v1.3"
  },
  "attributes": null
}