{
  "response": "OK",
  "metadata_uri": "ipfs://bafkreigvxnbof56nphxq3oen3jgnbznzdmlsb4beop43b5ev7wqzalpxw4",
  "name": "Fantasy Planet #3187",
  "description": "Which Fantasy Planet will you get?",
  "file_url": "https://ipfs.io/ipfs/bafybeihyajgw5iqn5x3ghnv64ogh7izctjjh3lksqjvh56bn32lbcehiaq",
  "external_url": "https://www.fantasyplanets.world",
  "animation_url": null,
  "custom_fields": {
    "edition": 1,
    "date": 1653956511160,
    "compiler": "Fantasy Art Generator v1.3"
  },
  "attributes": null
}