{
  "response": "OK",
  "metadata_uri": "ipfs://bafkreiapvwg4pdhcah3cw5uofkgsmbcqozhcbb3tfx4cksk743loyfgyiq",
  "name": "Fantasy Planet #931",
  "description": "Which Fantasy Planet will you get?",
  "file_url": "https://ipfs.io/ipfs/bafybeihyajgw5iqn5x3ghnv64ogh7izctjjh3lksqjvh56bn32lbcehiaq",
  "external_url": "https://www.fantasyplanets.world",
  "animation_url": null,
  "custom_fields": {
    "edition": 1,
    "date": 1653799184736,
    "compiler": "Fantasy Art Generator v1.3"
  },
  "attributes": null
}